ros_hirac_camera_topic/__init__.py
ros_hirac_camera_topic/script.py
ros_hirac_camera_topic-1.0.3.dist-info/METADATA
ros_hirac_camera_topic-1.0.3.dist-info/WHEEL
ros_hirac_camera_topic-1.0.3.dist-info/top_level.txt
ros_hirac_camera_topic-1.0.3.dist-info/RECORD
